Workbook
Name Acquisition_Cost: Campaign_Analysis!$K$2:$K$2002
Name Campaign_ID: Campaign_Analysis!$A$2:$A$2002
Name Campaign_Performance_Rating: Campaign_Analysis!$Z$2:$Z$2002
Name Campaign_Type: Campaign_Analysis!$B$2:$B$2002
Name Channel_Used: Campaign_Analysis!$E$2:$E$2002
Name Clicks: Campaign_Analysis!$G$2:$G$2002
Name Conversions: Campaign_Analysis!$I$2:$I$2002
Name Cost_Per_Acquisition: Campaign_Analysis!$K$2:$K$2002
Name Cost_per_Lead__CPL: Campaign_Analysis!$X$2:$X$2002
Name CPC: Campaign_Analysis!$V$2:$V$2002
Name CTR: Campaign_Analysis!$U$2:$U$2002
Name Customer_Segment: Campaign_Analysis!$O$2:$O$2002
Name Date: Campaign_Analysis!$P$2:$P$2002
Name Day: Campaign_Analysis!$S$2:$S$2002
Name Duration: Campaign_Analysis!$D$2:$D$2002
Name Engagement_Score: Campaign_Analysis!$N$2:$N$2002
Name Impressions: Campaign_Analysis!$F$2:$F$2002
Name Leads: Campaign_Analysis!$H$2:$H$2002
Name Month: Campaign_Analysis!$Q$2:$Q$2002
Name Overall_Conversion_Rate: Campaign_Analysis!$W$2:$W$2002
Name Profit: Campaign_Analysis!$Y$2:$Y$2002
Name Quarter: Campaign_Analysis!$T$2:$T$2002
Name Revenue: Campaign_Analysis!$J$2:$J$2002
Name ROI: Campaign_Analysis!$M$2:$M$2002
Name Slicer_Campaign_Type: #N/A
Name Slicer_Customer_Segment: #N/A
Name Slicer_Month: #N/A
Name Slicer_Quarter: #N/A
Name Target_Audience: Campaign_Analysis!$C$2:$C$2002
Name Total_Campaign_Cost: Campaign_Analysis!$L$2:$L$2002
Name Year: Campaign_Analysis!$R$2:$R$2002

Sheet Home

Sheet Raw_Data
A1: Campaign_ID | B1: Campaign_Type | C1: Target_Audience | D1: Duration | E1: Channel_Used | F1: Impressions | G1: Clicks | H1: Leads | I1: Conversions | J1: Revenue | K1: Acquisition_Cost | L1: ROI | M1: Engagement_Score | N1: Customer_Segment | O1: Date
A2: NY-CMP-1000 | B2: Social Media | C2: College Students | D2: 21 | E2: WhatsApp, YouTube | F2: 57804 | G2: 6156 | H2: 3616 | I2: 2355 | J2: 1867515 | K2: 111.03 | L2: 6.14 | M2: 20.98 | N2: College Students | O2: 45776
A3: NY-CMP-1001 | B3: Paid Ads | C3: Tier 2 City Customers | D3: 18 | E3: YouTube | F3: 91801 | G3: 3321 | H3: 1971 | I3: 1357 | J3: 1046247 | K3: 180.83 | L3: 3.26 | M3: 7.24 | N3: College Students | O3: 45753
A4: NY-CMP-1002 | B4: Influencer | C4: Youth | D4: 23 | E4: WhatsApp, Google, YouTube | F4: 15536 | G4: 2182 | H4: 952 | I4: 755 | J4: 197055 | K4: 90.6 | L4: 1.88 | M4: 25.03 | N4: College Students | O4: 45671
A5: NY-CMP-1003 | B5: Email | C5: Working Women | D5: 18 | E5: YouTube, Facebook, Instagram | F5: 88114 | G5: 8413 | H5: 2231 | I5: 947 | J5: 376906 | K5: 249.07 | L5: 0.6 | M5: 13.15 | N5: College Students | O5: 45812
A6: NY-CMP-1004 | B6: Paid Ads | C6: College Students | D6: 10 | E6: Facebook, Instagram | F6: 96871 | G6: 3743 | H6: 2060 | I6: 1258 | J6: 518296 | K6: 228.6 | L6: 0.8 | M6: 7.29 | N6: Tier 2 City Customers | O6: 45655
A7: NY-CMP-1005 | B7: Influencer | C7: Youth | D7: 26 | E7: Email, Instagram | F7: 83919 | G7: 7497 | H7: 2061 | I7: 1555 | J7: 877020 | K7: 137.79 | L7: 3.09 | M7: 13.24 | N7: Premium Shoppers | O7: 45558
A8: NY-CMP-1006 | B8: Paid Ads | C8: College Students | D8: 21 | E8: YouTube, Google, WhatsApp | F8: 82267 | G8: 5534 | H8: 1873 | I8: 1386 | J8: 633402 | K8: 210.17 | L8: 1.17 | M8: 10.69 | N8: Youth | O8: 45536
A9: NY-CMP-1007 | B9: Social Media | C9: Working Women | D9: 6 | E9: Instagram, WhatsApp, Google | F9: 32482 | G9: 2665 | H9: 1488 | I9: 925 | J9: 326525 | K9: 147.29 | L9: 1.4 | M9: 15.63 | N9: Tier 2 City Customers | O9: 45808
A10: NY-CMP-1008 | B10: Influencer | C10: Premium Shoppers | D10: 27 | E10: Facebook, WhatsApp, Email | F10: 73813 | G10: 8680 | H10: 5031 | I10: 2551 | J10: 1058665 | K10: 87.74 | L10: 3.73 | M10: 22.03 | N10: Tier 2 City Customers | O10: 45740
A11: NY-CMP-1009 | B11: Social Media | C11: College Students | D11: 11 | E11: Email | F11: 88895 | G11: 6284 | H11: 1600 | I11: 858 | J11: 603174 | K11: 269.82 | L11: 1.61 | M11: 9.83 | N11: Youth | O11: 45776
A12: NY-CMP-1010 | B12: SEO | C12: Working Women | D12: 5 | E12: Google, Instagram | F12: 59141 | G12: 1556 | H12: 580 | I12: 221 | J12: 121550 | K12: 357.66 | L12: 0.54 | M12: 3.99 | N12: Working Women | O12: 45591
A13: NY-CMP-1011 | B13: SEO | C13: Youth | D13: 7 | E13: Facebook, YouTube | F13: 39696 | G13: 5623 | H13: 1136 | I13: 661 | J13: 286874 | K13: 163.52 | L13: 1.65 | M13: 18.69 | N13: Premium Shoppers | O13: 45647
... A2002: NY-CMP-3000 | B2002: SEO | C2002: Premium Shoppers | D2002: 25 | E2002: Instagram | F2002: 25025 | G2002: 2683 | H2002: 1251 | I2002: 730 | J2002: 383980 | K2002: 269.91 | L2002: 0.95 | M2002: 18.64 | N2002: Tier 2 City Customers | O2002: 45797

Sheet Campaign_Analysis
A1: Campaign_ID | B1: Campaign_Type | C1: Target_Audience | D1: Duration | E1: Channel_Used | F1: Impressions | G1: Clicks | H1: Leads | I1: Conversions | J1: Revenue | K1: Cost_Per_Acquisition | L1: Total_Campaign_Cost | M1: ROI | N1: Engagement_Score | O1: Customer_Segment | P1: Date | Q1: Month | R1: Year | S1: Day | T1: Quarter | U1: CTR(%) | V1: CPC | W1: Overall Conversion Rate (%) | X1: Cost per Lead (CPL) | Y1: Profit | Z1: Campaign Performance Rating
A2: NY-CMP-1000 | B2: Social Media | C2: College Students | D2: 21 | E2: WhatsApp, YouTube | F2: 57804 | G2: 6156 | H2: 3616 | I2: 2355 | J2: 1867515 | K2: 111.03 | L2: =Campaign_Table[[#This Row],[Conversions]]*Campaign_Table[[#This Row],[Cost_Per_Acquisition]] -> 261475.65 | M2: 6.14 | N2: 20.98 | O2: College Students | P2: 45776 | Q2: =TEXT(Campaign_Table[[#This Row],[Date]],"mmmm") -> April | R2: =YEAR(Campaign_Table[[#This Row],[Date]]) -> 2025 | S2: =TEXT(Campaign_Table[[#This Row],[Date]],"dddd") -> Tuesday | T2: ="Q" & ROUNDUP(MONTH(Campaign_Table[[#This Row],[Date]])/3,0) -> Q2 | U2: =IFERROR(Clicks/Impressions,0) -> 0.10649782 | V2: =IFERROR(Campaign_Table[[#This Row],[Total_Campaign_Cost]]/Campaign_Table[[#This Row],[Clicks]],0) -> 42.474927 | W2: =IFERROR(Conversions/Clicks,0) -> 0.38255361 | X2: =IFERROR(Campaign_Table[[#This Row],[Total_Campaign_Cost]]/Campaign_Table[[#This Row],[Leads]],0) -> 72.310744 | Y2: =Revenue-Total_Campaign_Cost -> 1606039.4 | Z2: =IF(Campaign_Table[[#This Row],[ROI]]>=3,"Excellent",IF(Campaign_Table[[#This Row],[ROI]]>=1,"Good",IF(Campaign_Table[[#This Row],[ROI]]>=0,"Average","Poor"))) -> Excellent
A3: NY-CMP-1001 | B3: Paid Ads | C3: Tier 2 City Customers | D3: 18 | E3: YouTube | F3: 91801 | G3: 3321 | H3: 1971 | I3: 1357 | J3: 1046247 | K3: 180.83 | L3: =Campaign_Table[[#This Row],[Conversions]]*Campaign_Table[[#This Row],[Cost_Per_Acquisition]] -> 245386.31 | M3: 3.26 | N3: 7.24 | O3: College Students | P3: 45753 | Q3: =TEXT(Campaign_Table[[#This Row],[Date]],"mmmm") -> April | R3: =YEAR(Campaign_Table[[#This Row],[Date]]) -> 2025 | S3: =TEXT(Campaign_Table[[#This Row],[Date]],"dddd") -> Sunday | T3: ="Q" & ROUNDUP(MONTH(Campaign_Table[[#This Row],[Date]])/3,0) -> Q2 | U3: =IFERROR(Clicks/Impressions,0) -> 0.036176077 | V3: =IFERROR(Campaign_Table[[#This Row],[Total_Campaign_Cost]]/Campaign_Table[[#This Row],[Clicks]],0) -> 73.889283 | W3: =IFERROR(Conversions/Clicks,0) -> 0.40861186 | X3: =IFERROR(Campaign_Table[[#This Row],[Total_Campaign_Cost]]/Campaign_Table[[#This Row],[Leads]],0) -> 124.49838 | Y3: =Revenue-Total_Campaign_Cost -> 800860.69 | Z3: =IF(Campaign_Table[[#This Row],[ROI]]>=3,"Excellent",IF(Campaign_Table[[#This Row],[ROI]]>=1,"Good",IF(Campaign_Table[[#This Row],[ROI]]>=0,"Average","Poor"))) -> Excellent
A4: NY-CMP-1002 | B4: Influencer | C4: Youth | D4: 23 | E4: WhatsApp, Google, YouTube | F4: 15536 | G4: 2182 | H4: 952 | I4: 755 | J4: 197055 | K4: 90.6 | L4: =Campaign_Table[[#This Row],[Conversions]]*Campaign_Table[[#This Row],[Cost_Per_Acquisition]] -> 68403 | M4: 1.88 | N4: 25.03 | O4: College Students | P4: 45671 | Q4: =TEXT(Campaign_Table[[#This Row],[Date]],"mmmm") -> January | R4: =YEAR(Campaign_Table[[#This Row],[Date]]) -> 2025 | S4: =TEXT(Campaign_Table[[#This Row],[Date]],"dddd") -> Tuesday | T4: ="Q" & ROUNDUP(MONTH(Campaign_Table[[#This Row],[Date]])/3,0) -> Q1 | U4: =IFERROR(Clicks/Impressions,0) -> 0.14044799 | V4: =IFERROR(Campaign_Table[[#This Row],[Total_Campaign_Cost]]/Campaign_Table[[#This Row],[Clicks]],0) -> 31.348763 | W4: =IFERROR(Conversions/Clicks,0) -> 0.34601283 | X4: =IFERROR(Campaign_Table[[#This Row],[Total_Campaign_Cost]]/Campaign_Table[[#This Row],[Leads]],0) -> 71.851891 | Y4: =Revenue-Total_Campaign_Cost -> 128652 | Z4: =IF(Campaign_Table[[#This Row],[ROI]]>=3,"Excellent",IF(Campaign_Table[[#This Row],[ROI]]>=1,"Good",IF(Campaign_Table[[#This Row],[ROI]]>=0,"Average","Poor"))) -> Good
A5: NY-CMP-1003 | B5: Email | C5: Working Women | D5: 18 | E5: YouTube, Facebook, Instagram | F5: 88114 | G5: 8413 | H5: 2231 | I5: 947 | J5: 376906 | K5: 249.07 | L5: =Campaign_Table[[#This Row],[Conversions]]*Campaign_Table[[#This Row],[Cost_Per_Acquisition]] -> 235869.29 | M5: 0.6 | N5: 13.15 | O5: College Students | P5: 45812 | Q5: =TEXT(Campaign_Table[[#This Row],[Date]],"mmmm") -> June | R5: =YEAR(Campaign_Table[[#This Row],[Date]]) -> 2025 | S5: =TEXT(Campaign_Table[[#This Row],[Date]],"dddd") -> Wednesday | T5: ="Q" & ROUNDUP(MONTH(Campaign_Table[[#This Row],[Date]])/3,0) -> Q2 | U5: =IFERROR(Clicks/Impressions,0) -> 0.095478585 | V5: =IFERROR(Campaign_Table[[#This Row],[Total_Campaign_Cost]]/Campaign_Table[[#This Row],[Clicks]],0) -> 28.036288 | W5: =IFERROR(Conversions/Clicks,0) -> 0.11256389 | X5: =IFERROR(Campaign_Table[[#This Row],[Total_Campaign_Cost]]/Campaign_Table[[#This Row],[Leads]],0) -> 105.72357 | Y5: =Revenue-Total_Campaign_Cost -> 141036.71 | Z5: =IF(Campaign_Table[[#This Row],[ROI]]>=3,"Excellent",IF(Campaign_Table[[#This Row],[ROI]]>=1,"Good",IF(Campaign_Table[[#This Row],[ROI]]>=0,"Average","Poor"))) -> Average
A6: NY-CMP-1004 | B6: Paid Ads | C6: College Students | D6: 10 | E6: Facebook, Instagram | F6: 96871 | G6: 3743 | H6: 2060 | I6: 1258 | J6: 518296 | K6: 228.6 | L6: =Campaign_Table[[#This Row],[Conversions]]*Campaign_Table[[#This Row],[Cost_Per_Acquisition]] -> 287578.8 | M6: 0.8 | N6: 7.29 | O6: Tier 2 City Customers | P6: 45655 | Q6: =TEXT(Campaign_Table[[#This Row],[Date]],"mmmm") -> December | R6: =YEAR(Campaign_Table[[#This Row],[Date]]) -> 2024 | S6: =TEXT(Campaign_Table[[#This Row],[Date]],"dddd") -> Sunday | T6: ="Q" & ROUNDUP(MONTH(Campaign_Table[[#This Row],[Date]])/3,0) -> Q4 | U6: =IFERROR(Clicks/Impressions,0) -> 0.038639015 | V6: =IFERROR(Campaign_Table[[#This Row],[Total_Campaign_Cost]]/Campaign_Table[[#This Row],[Clicks]],0) -> 76.831098 | W6: =IFERROR(Conversions/Clicks,0) -> 0.33609404 | X6: =IFERROR(Campaign_Table[[#This Row],[Total_Campaign_Cost]]/Campaign_Table[[#This Row],[Leads]],0) -> 139.60136 | Y6: =Revenue-Total_Campaign_Cost -> 230717.2 | Z6: =IF(Campaign_Table[[#This Row],[ROI]]>=3,"Excellent",IF(Campaign_Table[[#This Row],[ROI]]>=1,"Good",IF(Campaign_Table[[#This Row],[ROI]]>=0,"Average","Poor"))) -> Average
A7: NY-CMP-1005 | B7: Influencer | C7: Youth | D7: 26 | E7: Email, Instagram | F7: 83919 | G7: 7497 | H7: 2061 | I7: 1555 | J7: 877020 | K7: 137.79 | L7: =Campaign_Table[[#This Row],[Conversions]]*Campaign_Table[[#This Row],[Cost_Per_Acquisition]] -> 214263.45 | M7: 3.09 | N7: 13.24 | O7: Premium Shoppers | P7: 45558 | Q7: =TEXT(Campaign_Table[[#This Row],[Date]],"mmmm") -> September | R7: =YEAR(Campaign_Table[[#This Row],[Date]]) -> 2024 | S7: =TEXT(Campaign_Table[[#This Row],[Date]],"dddd") -> Monday | T7: ="Q" & ROUNDUP(MONTH(Campaign_Table[[#This Row],[Date]])/3,0) -> Q3 | U7: =IFERROR(Clicks/Impressions,0) -> 0.089336146 | V7: =IFERROR(Campaign_Table[[#This Row],[Total_Campaign_Cost]]/Campaign_Table[[#This Row],[Clicks]],0) -> 28.579892 | W7: =IFERROR(Conversions/Clicks,0) -> 0.2074163 | X7: =IFERROR(Campaign_Table[[#This Row],[Total_Campaign_Cost]]/Campaign_Table[[#This Row],[Leads]],0) -> 103.96092 | Y7: =Revenue-Total_Campaign_Cost -> 662756.55 | Z7: =IF(Campaign_Table[[#This Row],[ROI]]>=3,"Excellent",IF(Campaign_Table[[#This Row],[ROI]]>=1,"Good",IF(Campaign_Table[[#This Row],[ROI]]>=0,"Average","Poor"))) -> Excellent
A8: NY-CMP-1006 | B8: Paid Ads | C8: College Students | D8: 21 | E8: YouTube, Google, WhatsApp | F8: 82267 | G8: 5534 | H8: 1873 | I8: 1386 | J8: 633402 | K8: 210.17 | L8: =Campaign_Table[[#This Row],[Conversions]]*Campaign_Table[[#This Row],[Cost_Per_Acquisition]] -> 291295.62 | M8: 1.17 | N8: 10.69 | O8: Youth | P8: 45536 | Q8: =TEXT(Campaign_Table[[#This Row],[Date]],"mmmm") -> September | R8: =YEAR(Campaign_Table[[#This Row],[Date]]) -> 2024 | S8: =TEXT(Campaign_Table[[#This Row],[Date]],"dddd") -> Sunday | T8: ="Q" & ROUNDUP(MONTH(Campaign_Table[[#This Row],[Date]])/3,0) -> Q3 | U8: =IFERROR(Clicks/Impressions,0) -> 0.067268771 | V8: =IFERROR(Campaign_Table[[#This Row],[Total_Campaign_Cost]]/Campaign_Table[[#This Row],[Clicks]],0) -> 52.637445 | W8: =IFERROR(Conversions/Clicks,0) -> 0.25045175 | X8: =IFERROR(Campaign_Table[[#This Row],[Total_Campaign_Cost]]/Campaign_Table[[#This Row],[Leads]],0) -> 155.52356 | Y8: =Revenue-Total_Campaign_Cost -> 342106.38 | Z8: =IF(Campaign_Table[[#This Row],[ROI]]>=3,"Excellent",IF(Campaign_Table[[#This Row],[ROI]]>=1,"Good",IF(Campaign_Table[[#This Row],[ROI]]>=0,"Average","Poor"))) -> Good
A9: NY-CMP-1007 | B9: Social Media | C9: Working Women | D9: 6 | E9: Instagram, WhatsApp, Google | F9: 32482 | G9: 2665 | H9: 1488 | I9: 925 | J9: 326525 | K9: 147.29 | L9: =Campaign_Table[[#This Row],[Conversions]]*Campaign_Table[[#This Row],[Cost_Per_Acquisition]] -> 136243.25 | M9: 1.4 | N9: 15.63 | O9: Tier 2 City Customers | P9: 45808 | Q9: =TEXT(Campaign_Table[[#This Row],[Date]],"mmmm") -> May | R9: =YEAR(Campaign_Table[[#This Row],[Date]]) -> 2025 | S9: =TEXT(Campaign_Table[[#This Row],[Date]],"dddd") -> Saturday | T9: ="Q" & ROUNDUP(MONTH(Campaign_Table[[#This Row],[Date]])/3,0) -> Q2 | U9: =IFERROR(Clicks/Impressions,0) -> 0.082045441 | V9: =IFERROR(Campaign_Table[[#This Row],[Total_Campaign_Cost]]/Campaign_Table[[#This Row],[Clicks]],0) -> 51.123171 | W9: =IFERROR(Conversions/Clicks,0) -> 0.34709193 | X9: =IFERROR(Campaign_Table[[#This Row],[Total_Campaign_Cost]]/Campaign_Table[[#This Row],[Leads]],0) -> 91.561324 | Y9: =Revenue-Total_Campaign_Cost -> 190281.75 | Z9: =IF(Campaign_Table[[#This Row],[ROI]]>=3,"Excellent",IF(Campaign_Table[[#This Row],[ROI]]>=1,"Good",IF(Campaign_Table[[#This Row],[ROI]]>=0,"Average","Poor"))) -> Good
A10: NY-CMP-1008 | B10: Influencer | C10: Premium Shoppers | D10: 27 | E10: Facebook, WhatsApp, Email | F10: 73813 | G10: 8680 | H10: 5031 | I10: 2551 | J10: 1058665 | K10: 87.74 | L10: =Campaign_Table[[#This Row],[Conversions]]*Campaign_Table[[#This Row],[Cost_Per_Acquisition]] -> 223824.74 | M10: 3.73 | N10: 22.03 | O10: Tier 2 City Customers | P10: 45740 | Q10: =TEXT(Campaign_Table[[#This Row],[Date]],"mmmm") -> March | R10: =YEAR(Campaign_Table[[#This Row],[Date]]) -> 2025 | S10: =TEXT(Campaign_Table[[#This Row],[Date]],"dddd") -> Monday | T10: ="Q" & ROUNDUP(MONTH(Campaign_Table[[#This Row],[Date]])/3,0) -> Q1 | U10: =IFERROR(Clicks/Impressions,0) -> 0.11759446 | V10: =IFERROR(Campaign_Table[[#This Row],[Total_Campaign_Cost]]/Campaign_Table[[#This Row],[Clicks]],0) -> 25.78626 | W10: =IFERROR(Conversions/Clicks,0) -> 0.29389401 | X10: =IFERROR(Campaign_Table[[#This Row],[Total_Campaign_Cost]]/Campaign_Table[[#This Row],[Leads]],0) -> 44.489115 | Y10: =Revenue-Total_Campaign_Cost -> 834840.26 | Z10: =IF(Campaign_Table[[#This Row],[ROI]]>=3,"Excellent",IF(Campaign_Table[[#This Row],[ROI]]>=1,"Good",IF(Campaign_Table[[#This Row],[ROI]]>=0,"Average","Poor"))) -> Excellent
A11: NY-CMP-1009 | B11: Social Media | C11: College Students | D11: 11 | E11: Email | F11: 88895 | G11: 6284 | H11: 1600 | I11: 858 | J11: 603174 | K11: 269.82 | L11: =Campaign_Table[[#This Row],[Conversions]]*Campaign_Table[[#This Row],[Cost_Per_Acquisition]] -> 231505.56 | M11: 1.61 | N11: 9.83 | O11: Youth | P11: 45776 | Q11: =TEXT(Campaign_Table[[#This Row],[Date]],"mmmm") -> April | R11: =YEAR(Campaign_Table[[#This Row],[Date]]) -> 2025 | S11: =TEXT(Campaign_Table[[#This Row],[Date]],"dddd") -> Tuesday | T11: ="Q" & ROUNDUP(MONTH(Campaign_Table[[#This Row],[Date]])/3,0) -> Q2 | U11: =IFERROR(Clicks/Impressions,0) -> 0.07069014 | V11: =IFERROR(Campaign_Table[[#This Row],[Total_Campaign_Cost]]/Campaign_Table[[#This Row],[Clicks]],0) -> 36.840477 | W11: =IFERROR(Conversions/Clicks,0) -> 0.13653724 | X11: =IFERROR(Campaign_Table[[#This Row],[Total_Campaign_Cost]]/Campaign_Table[[#This Row],[Leads]],0) -> 144.69098 | Y11: =Revenue-Total_Campaign_Cost -> 371668.44 | Z11: =IF(Campaign_Table[[#This Row],[ROI]]>=3,"Excellent",IF(Campaign_Table[[#This Row],[ROI]]>=1,"Good",IF(Campaign_Table[[#This Row],[ROI]]>=0,"Average","Poor"))) -> Good
A12: NY-CMP-1010 | B12: SEO | C12: Working Women | D12: 5 | E12: Google, Instagram | F12: 59141 | G12: 1556 | H12: 580 | I12: 221 | J12: 121550 | K12: 357.66 | L12: =Campaign_Table[[#This Row],[Conversions]]*Campaign_Table[[#This Row],[Cost_Per_Acquisition]] -> 79042.86 | M12: 0.54 | N12: 3.99 | O12: Working Women | P12: 45591 | Q12: =TEXT(Campaign_Table[[#This Row],[Date]],"mmmm") -> October | R12: =YEAR(Campaign_Table[[#This Row],[Date]]) -> 2024 | S12: =TEXT(Campaign_Table[[#This Row],[Date]],"dddd") -> Saturday | T12: ="Q" & ROUNDUP(MONTH(Campaign_Table[[#This Row],[Date]])/3,0) -> Q4 | U12: =IFERROR(Clicks/Impressions,0) -> 0.026310005 | V12: =IFERROR(Campaign_Table[[#This Row],[Total_Campaign_Cost]]/Campaign_Table[[#This Row],[Clicks]],0) -> 50.798753 | W12: =IFERROR(Conversions/Clicks,0) -> 0.14203085 | X12: =IFERROR(Campaign_Table[[#This Row],[Total_Campaign_Cost]]/Campaign_Table[[#This Row],[Leads]],0) -> 136.28079 | Y12: =Revenue-Total_Campaign_Cost -> 42507.14 | Z12: =IF(Campaign_Table[[#This Row],[ROI]]>=3,"Excellent",IF(Campaign_Table[[#This Row],[ROI]]>=1,"Good",IF(Campaign_Table[[#This Row],[ROI]]>=0,"Average","Poor"))) -> Average
A13: NY-CMP-1011 | B13: SEO | C13: Youth | D13: 7 | E13: Facebook, YouTube | F13: 39696 | G13: 5623 | H13: 1136 | I13: 661 | J13: 286874 | K13: 163.52 | L13: =Campaign_Table[[#This Row],[Conversions]]*Campaign_Table[[#This Row],[Cost_Per_Acquisition]] -> 108086.72 | M13: 1.65 | N13: 18.69 | O13: Premium Shoppers | P13: 45647 | Q13: =TEXT(Campaign_Table[[#This Row],[Date]],"mmmm") -> December | R13: =YEAR(Campaign_Table[[#This Row],[Date]]) -> 2024 | S13: =TEXT(Campaign_Table[[#This Row],[Date]],"dddd") -> Saturday | T13: ="Q" & ROUNDUP(MONTH(Campaign_Table[[#This Row],[Date]])/3,0) -> Q4 | U13: =IFERROR(Clicks/Impressions,0) -> 0.14165155 | V13: =IFERROR(Campaign_Table[[#This Row],[Total_Campaign_Cost]]/Campaign_Table[[#This Row],[Clicks]],0) -> 19.222251 | W13: =IFERROR(Conversions/Clicks,0) -> 0.11755291 | X13: =IFERROR(Campaign_Table[[#This Row],[Total_Campaign_Cost]]/Campaign_Table[[#This Row],[Leads]],0) -> 95.146761 | Y13: =Revenue-Total_Campaign_Cost -> 178787.28 | Z13: =IF(Campaign_Table[[#This Row],[ROI]]>=3,"Excellent",IF(Campaign_Table[[#This Row],[ROI]]>=1,"Good",IF(Campaign_Table[[#This Row],[ROI]]>=0,"Average","Poor"))) -> Good
... A2002: NY-CMP-3000 | B2002: SEO | C2002: Premium Shoppers | D2002: 25 | E2002: Instagram | F2002: 25025 | G2002: 2683 | H2002: 1251 | I2002: 730 | J2002: 383980 | K2002: 269.91 | L2002: =Campaign_Table[[#This Row],[Conversions]]*Campaign_Table[[#This Row],[Cost_Per_Acquisition]] -> 197034.3 | M2002: 0.95 | N2002: 18.64 | O2002: Tier 2 City Customers | P2002: 45797 | Q2002: =TEXT(Campaign_Table[[#This Row],[Date]],"mmmm") -> May | R2002: =YEAR(Campaign_Table[[#This Row],[Date]]) -> 2025 | S2002: =TEXT(Campaign_Table[[#This Row],[Date]],"dddd") -> Tuesday | T2002: ="Q" & ROUNDUP(MONTH(Campaign_Table[[#This Row],[Date]])/3,0) -> Q2 | U2002: =IFERROR(Clicks/Impressions,0) -> 0.10721279 | V2002: =IFERROR(Campaign_Table[[#This Row],[Total_Campaign_Cost]]/Campaign_Table[[#This Row],[Clicks]],0) -> 73.438054 | W2002: =IFERROR(Conversions/Clicks,0) -> 0.27208349 | X2002: =IFERROR(Campaign_Table[[#This Row],[Total_Campaign_Cost]]/Campaign_Table[[#This Row],[Leads]],0) -> 157.50144 | Y2002: =Revenue-Total_Campaign_Cost -> 186945.7 | Z2002: =IF(Campaign_Table[[#This Row],[ROI]]>=3,"Excellent",IF(Campaign_Table[[#This Row],[ROI]]>=1,"Good",IF(Campaign_Table[[#This Row],[ROI]]>=0,"Average","Poor"))) -> Average

Sheet Dashboard
A1: CAMPAIGN PERFORMANCE & REVENUE ANALYSIS
A3: Total Revenue
A4: =GETPIVOTDATA("Revenue",Pivot_Table!$K$3) -> 1024747480
A6: Total Campaign Cost
A7: =GETPIVOTDATA("Total_Campaign_Cost",Pivot_Table!$K$6) -> 3.4876058e+08
A9: Total Profit
A10: =GETPIVOTDATA("Profit",Pivot_Table!$K$9) -> 6.759869e+08
A12: Average ROI
A13: =GETPIVOTDATA("ROI",Pivot_Table!$K$12) -> 2.768051
A15: Average CTR
A16: =GETPIVOTDATA("CTR(%)",Pivot_Table!$K$15) -> 0.085275834
A18: Total Clicks
A19: =GETPIVOTDATA("Clicks",Pivot_Table!$K$24) -> 9289123
A21: Total Impression
A22: =GETPIVOTDATA("Impressions",Pivot_Table!$K$21) -> 109170720
A24: Total Leads
A25: =GETPIVOTDATA("Leads",Pivot_Table!$K$27) -> 3703777
A27: Total Conversion
A28: =GETPIVOTDATA("Conversions",Pivot_Table!$K$18) -> 2051939
A30: Average CPC
A31: =GETPIVOTDATA("CPC",Pivot_Table!$K$33) -> 68.297907

Sheet Top_10_Campaign
A1: TOP 10 CAMPAIGN PERFORMANCE ANALYSIS
A3: Rank | B3: Campaign ID | C3: Revenue. | D3: Profit. | E3: Total_Campaign_Cost_ | F3: ROI. | G3: Leads. | H3: Conversions.
A4: =_xlfn.RANK.EQ(C4,$C$4:$C$13,0) -> 1 | B4: NY-CMP-1298 | C4: 3520822 | D4: 3251623.7 | E4: 269198.26 | F4: 12.08 | G4: 6768 | H4: 4987
A5: =_xlfn.RANK.EQ(C5,$C$4:$C$13,0) -> 2 | B5: NY-CMP-2805 | C5: 3147660 | D5: 2872852.8 | E5: 274807.2 | F5: 10.45 | G5: 5148 | H5: 4020
A6: =_xlfn.RANK.EQ(C6,$C$4:$C$13,0) -> 3 | B6: NY-CMP-2174 | C6: 3126600 | D6: 3071034 | E6: 55566 | F6: 55.27 | G6: 7739 | H6: 4050
A7: =_xlfn.RANK.EQ(C7,$C$4:$C$13,0) -> 4 | B7: NY-CMP-2404 | C7: 3123919 | D7: 2836105.9 | E7: 287813.06 | F7: 9.85 | G7: 5815 | H7: 4297
A8: =_xlfn.RANK.EQ(C8,$C$4:$C$13,0) -> 5 | B8: NY-CMP-2696 | C8: 2954388 | D8: 2710496.3 | E8: 243891.69 | F8: 11.11 | G8: 5696 | H8: 3867
A9: =_xlfn.RANK.EQ(C9,$C$4:$C$13,0) -> 6 | B9: NY-CMP-1227 | C9: 2827524 | D9: 2767082 | E9: 60442.02 | F9: 45.77 | G9: 8876 | H9: 4926
A10: =_xlfn.RANK.EQ(C10,$C$4:$C$13,0) -> 7 | B10: NY-CMP-2717 | C10: 2785468 | D10: 2615073.9 | E10: 170394.06 | F10: 15.35 | G10: 5970 | H10: 3754
A11: =_xlfn.RANK.EQ(C11,$C$4:$C$13,0) -> 8 | B11: NY-CMP-2329 | C11: 2681535 | D11: 2552146.7 | E11: 129388.28 | F11: 19.73 | G11: 5008 | H11: 3373
A12: =_xlfn.RANK.EQ(C12,$C$4:$C$13,0) -> 9 | B12: NY-CMP-2196 | C12: 2656440 | D12: 2496413 | E12: 160026.96 | F12: 15.6 | G12: 5050 | H12: 3768
A13: =_xlfn.RANK.EQ(C13,$C$4:$C$13,0) -> 10 | B13: NY-CMP-2599 | C13: 2599436 | D13: 2300198.6 | E13: 299237.4 | F13: 7.69 | G13: 6345 | H13: 3556

Sheet Analysis_Findings
B1: CAMPAIGN ANALYSIS & FINDINGS
B2: Business Question | C2: Finding
B3: How much revenue did all campaigns generate? | C3: ₹102.47 Cr Total revenue
B4: How much was invested in marketing? | C4: Total ₹34.88 Cr investment
B5: Was the marketing profitable? | C5: Yes. The campaigns generated a profit of ₹67.59 Cr, indicating strong overall profitability.
B6: What was the average return on investment? | C6: 2.77x, meaning every ₹1 invested returned approximately ₹2.77.
B7: Are customers engaging with the advertisements? | C7: Yes. The average CTR of 8.53% indicates healthy audience engagement.
B8: How many successful customer conversions were achieved? | C8: Over 2 million conversions, showing strong campaign effectiveness.
B9: Which marketing channel generated the highest revenue? | C9: Influencer Marketing
B10: Which campaign generated the least revenue? | C10: Social Media
B11: Which marketing channel should receive a higher budget? | C11: Influencer Marketing because it delivers the highest revenue and ROI.
B12: Which customer segment generates the highest revenue? | C12: College Students
B13: Which audience should marketing focus on? | C13: College Students and Premium Shoppers should remain priority target segments.
... B20: Top 10 Campaigns | C20: The Top 10 Campaign Analysis identifies the highest-performing campaigns based on Revenue, Profit, ROI, Leads, and Conversions for future strategy planning.

Sheet Insights_Recommendations
B1: EXECUTIVE INSIGHTS & RECOMMENDATIONS
B2: Insight | C2: Recommendation
B3: 💰 Revenue reached ₹102.47 Cr. | C3: Continue investing in high-performing campaigns to sustain growth.
B4: ⭐ Influencer Marketing generated the highest revenue. | C4: Increase budget for Influencer campaigns.
B5: 📉 Social Media generated the lowest revenue. | C5: Optimize Social Media targeting and campaign creatives.
B6: 🎯 College Students were the top customer segment. | C6: Continue prioritizing College Students in future campaigns.
B7: 🌱 Youth segment has growth potential. | C7: Launch targeted campaigns for Youth.
B8: 📅 October recorded the highest revenue. | C8: Increase marketing before peak seasons.
B9: 📈 Q2 achieved the highest ROI. | C9: Replicate successful Q2 campaign strategies throughout the year.
B10: 🔄 Funnel shows drop from Clicks to Conversions. | C10: Optimize landing pages and checkout.
B11: 🏆 Most campaigns were rated Excellent. | C11: Maintain and scale successful campaign strategies.
B12: 🔝 Top 10 campaigns drove the best results. | C12: Use them as benchmarks for future campaigns.

Sheet Pivot_Table
A1: PIVOT TABLES AND KPIs
A3: Row Labels | B3: Sum of Revenue | D3: Row Labels | E3: Average of ROI | G3: Row Labels | H3: Sum of Revenue | K3: Sum of Revenue
A4: Email | B4: 204718992 | D4: Email | E4: 2.7356992 | G4: College Students | H4: 216118666 | K4: 1024747480
A5: Influencer | B5: 220280781 | D5: Influencer | E5: 3.1091325 | G5: Premium Shoppers | H5: 212386886
A6: Paid Ads | B6: 197343503 | D6: Paid Ads | E6: 2.5096183 | G6: Tier 2 City Customers | H6: 203466935 | K6: Sum of Total_Campaign_Cost
A7: SEO | B7: 203907637 | D7: SEO | E7: 3.0251508 | G7: Working Women | H7: 207636810 | K7: 3.4876058e+08
A8: Social Media | B8: 198496567 | D8: Social Media | E8: 2.4554327 | G8: Youth | H8: 185138183
A9: Grand Total | B9: 1024747480 | D9: Grand Total | E9: 2.768051 | G9: Grand Total | H9: 1024747480 | K9: Sum of Profit
K10: 6.759869e+08
A12: Row Labels | B12: Monthly Revenue Trend | D12: Row Labels | E12: Count of Campaign_ID | G12: Row Labels | H12: Sum of Profit | I12: Profit vs Total Campaign Cost | K12: Average of ROI
A13: January | B13: 89704123 | D13: Average | E13: 450 | G13: Average | H13: 39977059 | I13: 86386017 | K13: 2.768051
A14: February | B14: 80335321 | D14: Excellent | E14: 585 | G14: Excellent | H14: 5.2171382e+08 | I14: 77209441
A15: March | B15: 86340974 | D15: Good | E15: 488 | G15: Good | H15: 1.5667989e+08 | I15: 84007033 | K15: Average of CTR(%)
A16: April | B16: 97359169 | D16: Poor | E16: 478 | G16: Poor | H16: -42383871 | I16: 1.0115809e+08 | K16: 0.085275834
A17: May | B17: 98415583 | D17: Grand Total | E17: 2001 | G17: Grand Total | H17: 6.759869e+08 | I17: 3.4876058e+08
A18: June | B18: 29631206 | K18: Sum of Conversions
A19: July | B19: 90509390 | D19: Row Labels | E19: Average of ROI | G19: Marketing Funnel | H19: Total | K19: 2051939
A20: August | B20: 99259407 | D20: Q1 | E20: 2.5372023 | G20: Sum of Impressions | H20: 109170720
A21: September | B21: 63437783 | D21: Q2 | E21: 3.0408197 | G21: Sum of Clicks | H21: 9289123 | K21: Sum of Impressions
A22: October | B22: 106670959 | D22: Q3 | E22: 2.6039961 | G22: Sum of Leads | H22: 3703777 | K22: 109170720
A23: November | B23: 87358983 | D23: Q4 | E23: 2.9368609 | G23: Sum of Conversions | H23: 2051939
A24: December | B24: 95724582 | D24: Grand Total | E24: 2.768051 | K24: Sum of Clicks
A25: Grand Total | B25: 1024747480 | K25: 9289123
K27: Sum of Leads
K28: 3703777
K30: Average of Cost per Lead (CPL)
K31: 190.14797
K33: Average of CPC
K34: 68.297907
